topsis/102003410.py
topsis/__init__.py
Topsis_Ishan_102003410-0.1.dist-info/LICENSE.txt
Topsis_Ishan_102003410-0.1.dist-info/METADATA
Topsis_Ishan_102003410-0.1.dist-info/WHEEL
Topsis_Ishan_102003410-0.1.dist-info/entry_points.txt
Topsis_Ishan_102003410-0.1.dist-info/top_level.txt
Topsis_Ishan_102003410-0.1.dist-info/RECORD
